Flask_Slacker-0.0.2.dist-info/METADATA
Flask_Slacker-0.0.2.dist-info/RECORD
Flask_Slacker-0.0.2.dist-info/WHEEL
Flask_Slacker-0.0.2.dist-info/top_level.txt
flask_slacker/__init__.py
